async_sender/__init__.py
async_sender/_version.py
async_sender/api.py
async_sender-3.0.0.dist-info/LICENSE
async_sender-3.0.0.dist-info/METADATA
async_sender-3.0.0.dist-info/WHEEL
async_sender-3.0.0.dist-info/top_level.txt
async_sender-3.0.0.dist-info/RECORD
