Metadata-Version: 2.1
Name: async-sender
Version: 3.0.0
Summary: AsyncSender is a tiny module for SMTP mail sending, Inspired by Sender.
Home-page: https://github.com/theruziev/async_sender
Author: Bakhtiyor Ruziev
Author-email: rbakhtiyor+github@gmail.com
License: UNKNOWN
Keywords: email,sender,smtp,asyncio
Platform: UNKNOWN
Classifier: Development Status :: 3 - Alpha
Classifier: Intended Audience :: Developers
Classifier: Programming Language :: Python
Classifier: Programming Language :: Python :: 3.8
Classifier: Programming Language :: Python :: 3.9
Classifier: Programming Language :: Python :: 3.10
Classifier: Programming Language :: Python :: 3.11
Classifier: Programming Language :: Python :: Implementation :: CPython
Classifier: Topic :: Software Development :: Libraries :: Python Modules
Classifier: License :: OSI Approved :: MIT License
License-File: LICENSE
Requires-Dist: aiosmtplib (==3.0.1)
